vibeflow/__init__.py
vibeflow/cache.py
vibeflow/client.py
vibeflow/prompts.py
vibeflow/testing.py
vibeflow/vibe.py
vibeflow-0.0.5.dist-info/licenses/LICENSE
vibeflow-0.0.5.dist-info/METADATA
vibeflow-0.0.5.dist-info/WHEEL
vibeflow-0.0.5.dist-info/top_level.txt
vibeflow-0.0.5.dist-info/RECORD
