Metadata-Version: 2.4
Name: vibeflow
Version: 0.0.5
Summary: vibeflow - effortless python functions
Author: Stoyan Stoyanov
Project-URL: Homepage, https://github.com/stoyan-stoyanov/vibeflow
Project-URL: github, https://github.com/stoyan-stoyanov/vibeflow
Classifier: Programming Language :: Python :: 3
Classifier: License :: OSI Approved :: MIT License
Classifier: Operating System :: OS Independent
Requires-Python: >=3.9
License-File: LICENSE
Requires-Dist: openai==1.93.1
Requires-Dist: pytest==8.4.1
Requires-Dist: pytest-asyncio==1.0.0
Requires-Dist: black==25.1.0
Requires-Dist: mkdocs-material==9.6.15
Requires-Dist: mkdocstrings==0.29.1
Requires-Dist: mkdocstrings-python==1.16.12
Dynamic: license-file
